setup.py
iva_benchmark/__init__.py
iva_benchmark/embedders.py
iva_benchmark/embeddings_processor.py
iva_benchmark/factory.py
iva_benchmark/metrics.py
iva_benchmark/utils.py
iva_benchmark.egg-info/PKG-INFO
iva_benchmark.egg-info/SOURCES.txt
iva_benchmark.egg-info/dependency_links.txt
iva_benchmark.egg-info/not-zip-safe
iva_benchmark.egg-info/top_level.txt