Metadata-Version: 1.0
Name: iva-benchmark
Version: 0.0
Summary: IVA Cognitive Benchmark 
Home-page: UNKNOWN
Author: UNKNOWN
Author-email: n.izvarina@iva-cv.ru
License: UNKNOWN
Platform: UNKNOWN
